{"url":"https://csunibo.github.io/algebra-e-geometria/appunti","name":"appunti","path":"appunti","directories":null,"files":[{"url":"https://www.notion.so/Algebra-a65a99336ccc499ead0637365a3bd0cd","mime":"text/statik-link","name":"notion-di-alex","path":"appunti/notion-di-alex"},{"url":"https://flecart-notes.notion.site/Algebra-lineare-86d28e35350f4f88a0db4349fad5a984","mime":"text/statik-link","name":"notion-di-angelo-huang","path":"appunti/notion-di-angelo-huang"},{"url":"https://www.notion.so/Algebra-e-geometria-00d4b98a5d974879aaf39457ede3261a","mime":"text/statik-link","name":"notion-di-luizo","path":"appunti/notion-di-luizo"}],"size":"4.1 kB","time":"2022-06-26T09:12:25.542362755Z"}